smcode/__init__.py
smcode/selenium.py
smcode/telegram.py
smcode-0.0.6.dist-info/METADATA
smcode-0.0.6.dist-info/WHEEL
smcode-0.0.6.dist-info/top_level.txt
smcode-0.0.6.dist-info/RECORD
