Metadata-Version: 2.1
Name: smcode
Version: 0.0.6
Summary: Selenium for Showm Company
Home-page: 
Maintainer-email: fredzenobius@gmail.com
Classifier: Programming Language :: Python :: 3
Classifier: License :: OSI Approved :: MIT License
Classifier: Operating System :: Microsoft :: Windows
Requires-Python: >=3.6
Requires-Dist: selenium ==3.141.0
Requires-Dist: urllib3 ==1.26.12
Requires-Dist: requests
Requires-Dist: pyperclip
Requires-Dist: chromedriver-autoinstaller
Requires-Dist: fake-useragent
Requires-Dist: tqdm
